catcoocc/__init__.py
catcoocc/__main__.py
catcoocc/correlation.py
catcoocc/scorer.py
catcoocc/utils.py
docs/Demo.ipynb
docs/demo.py
docs/zychlinski_chi2_xy.png
docs/zychlinski_chi2_yx.png
docs/zychlinski_mle_xy.png
docs/zychlinski_mle_yx.png
docs/zychlinski_tresoldi_xy.png
docs/zychlinski_tresoldi_yx.png
resources/README.md
resources/cmudict.sample100.tsv
resources/cmudict.sample1000.tsv
resources/cmudict.tsv
resources/galapagos.tsv
resources/mushroom-small.tsv
resources/mushrooms.tsv
resources/pokemon.tsv
resources/toy.tsv
resources/wiktionary.tsv
catcoocc-0.2.3.dist-info/AUTHORS.md
catcoocc-0.2.3.dist-info/LICENSE
catcoocc-0.2.3.dist-info/METADATA
catcoocc-0.2.3.dist-info/WHEEL
catcoocc-0.2.3.dist-info/entry_points.txt
catcoocc-0.2.3.dist-info/top_level.txt
catcoocc-0.2.3.dist-info/RECORD
