Metadata-Version: 2.1
Name: catcoocc
Version: 0.2.3
Summary: Methods for symmetric and asymmetric analysis of categorical co-occurrences
Home-page: https://github.com/tresoldi/catcoocc
Author: Tiago Tresoldi
Author-email: tiago.tresoldi@lingfil.uu.se
License: MIT
Keywords: co-occurrence,cooccurrence,categorical variables,mutual information,scorer
Classifier: License :: OSI Approved :: MIT License
Classifier: Programming Language :: Python :: 3
Classifier: Operating System :: OS Independent
Classifier: Topic :: Software Development :: Libraries
License-File: LICENSE
License-File: AUTHORS.md
Requires-Dist: numpy
Requires-Dist: scipy
Requires-Dist: tabulate
